<?xml version="1.0" encoding="utf-8"?>
<language>
  <page id="61552" voice="no">
	<!--M1- Travel Mule-->
	<t id="1001">M1- 贸易骡子\(单站贸易\)</t>
	<t id="1002">基点空间站</t>
	<t id="1003">最大星门距离</t>
	<t id="1004">利润覆盖</t>
	<t id="1005">锁定自定义商品列表</t>
	<t id="1006">商品 \(默认全部\)</t>
	<t id="1007">装载比例</t>
	<t id="1008">目标NPC造船厂</t>
	<t id="1009">目标所有NPC空间站</t>
	<t id="1010">自定义目标列表 (替换 '目标' 选项)</t>
	
	<t id="1101">在空间站之间运送物资</t>
	<t id="1102">基点空间站</t>
	<t id="1103">最大销售距离</t>
	<t id="1104">自有空间站购买价格调整，0=出售所有商品，不考虑交易报价。100=服从空间站管理员的购买提议。</t>
	<t id="1105">锁定用户选择，否则每次调用脚本时都需要擦除它</t>
	<t id="1106">在贸易中考虑哪些商品</t>
	<t id="1107">贸易将占货舱的百分比。</t>
	<t id="1108">分配与所有NPC船厂、空间站和装备坞进行贸易。</t>
	<t id="1109">分配与所有NPC空间站进行贸易。</t>
	<t id="1110">手动选择要访问的点。</t>
	
    <!--M2- stationmule-->
    <t id="2001">M2- 空间站骡子\(2站互通\)</t>
	<t id="2002">基点空间站</t>
	<t id="2003">目标空间站</t>
	<t id="2004">分配到空间站</t>
	<t id="2005">包括能量电池</t>
	<t id="2006">包括食物和药物</t>
	<t id="2007">卖方优先权</t>
	<t id="2008">禁止违法商品</t>
	<t id="2009">仅非法商品</t>
	<t id="2010">双向贸易</t>
	<t id="2011">退货卖家优先权</t>
	<t id="2012">禁止系统内交易</t>
	<t id="2013">允许低货仓交易</t>
	<t id="2014">强制卖出</t>
	
	<t id="2101">在空间站之间运送物资</t>
	<t id="2102">基点空间站</t>
	<t id="2103">接收空间站</t>
	<t id="2104">如果是玩家，就分配给源空间站。</t>
	<t id="2105">包括电源中的能量电池</t>
	<t id="2106">包括食物和药品</t>
	<t id="2107">把优先权放在清空卖方的存货上</t>
	<t id="2108">从不买卖非法商品</t>
	<t id="2109">只交易非法商品</t>
	<t id="2110">在空间站之间来回交易</t>
	<t id="2111">卖方退货优先权</t>
	<t id="2112">禁止系统中所有游戏者对象空闲时进行交易</t>
	<t id="2113">允许低于50%的货物交易，80%的系统交易</t>
	<t id="2114">允许骡子强迫目标购买所有出售的货源。</t>
	
	<!--M3- Distribute Mule-->
	<t id="3001">M3- 物流骡子\(1对多货物分发\)</t>
	<t id="3002">源空间站</t>
	<t id="3003">最小仓储水平</t>
	<t id="3004">保持仓储水平</t>
	<t id="3005">最大仓储水平</t>
	<t id="3006">商品列表 \(默认全部\)</t>
	<t id="3007">目标仓库</t>
	
	<t id="3101">在仓库之间运送物资</t>
	<t id="3102">来源空间站</t>
	<t id="3103">每个仓库的最小存储量</t>
	<t id="3104">每个仓库应该保持的正常存储量</t>
	<t id="3105">每个仓库的最大存储量</t>
	<t id="3106">商品列表</t>
	<t id="3107">访问列表</t>
	
	<!--M4- Supply Mule-->
	<t id="4001">M4- 采购骡子\(满足特定或区域需求\)</t>
	<t id="4002">基点 空间站/星区</t>
	<t id="4003">分配到空间站下属</t>
	<t id="4004">最大活动范围</t>
	<t id="4005">仅服务基点空间站/星区</t>
	<t id="4006">允许玩家供应商</t>
	<t id="4007">允许AI供应商</t>
	<t id="4008">允许建材</t>
	<t id="4009">允许原材料</t>
	<t id="4010">允许中间产物</t>
	<t id="4011">允许商品</t>
	<t id="4012">锁定自定义商品列表</t>
	<t id="4013">商品 (默认全部)</t>
	<t id="4014">最大交易次数</t>
	<t id="4015">玩家购买模式</t>
	<t id="4016">仅限玩家空间站</t>
	<t id="4017">仅限建材仓库</t>
	<t id="4018">仅限工厂仓库</t>
	<t id="4019">基点 空间站/星区</t>
	<t id="4020">分配到空间站下属</t>
	<t id="4021">满仓最大交易次数</t>
	
	<t id="4101">供应指定空间站或星区的需求</t>
	<t id="4102">基点</t>
	<t id="4103">如果是玩家的话，分配给空间站下属。</t>
	<t id="4104">最大购买距离</t>
	<t id="4105">将只服务于配置的源站</t>
	<t id="4106">允许从玩家空间站购买</t>
	<t id="4107">允许从AI空间站购买</t>
	<t id="4108">允许购买建材</t>
	<t id="4109">允许购买原材料</t>
	<t id="4110">允许购买中间产物</t>
	<t id="4111">允许购买商品</t>
	<t id="4112">锁定用户选择，否则每次调用脚本时都需要清除</t>
	<t id="4113">商品清单</t>
	<t id="4114">满仓最大允许交易次数</t>
	<t id="4115">自有空间站交易价格调整, 0=忽略经理价格 100= 服从空间站经理价格</t>
	<t id="4116">仅从玩家空间站购买</t>
	<t id="4117">仅限供应建材仓库</t>
	<t id="4118">只向工厂供应产品</t>
	<t id="4119">源空间站</t>
	<t id="4120">如果是玩家的话，分配给空间站下属。</t>
	<t id="4121">满仓最大允许交易次数</t>
  </page>
</language>